README.md
setup.py
pulumi_libp2p/__init__.py
pulumi_libp2p/_enums.py
pulumi_libp2p/_utilities.py
pulumi_libp2p/key.py
pulumi_libp2p/provider.py
pulumi_libp2p/pulumi-plugin.json
pulumi_libp2p/py.typed
pulumi_libp2p.egg-info/PKG-INFO
pulumi_libp2p.egg-info/SOURCES.txt
pulumi_libp2p.egg-info/dependency_links.txt
pulumi_libp2p.egg-info/not-zip-safe
pulumi_libp2p.egg-info/requires.txt
pulumi_libp2p.egg-info/top_level.txt