Metadata-Version: 2.1
Name: pulumi-libp2p
Version: 1.0.4
Summary: UNKNOWN
Home-page: UNKNOWN
License: UNKNOWN
Platform: UNKNOWN
